fawx/__init__.py
fawx-0.0.5.dist-info/METADATA
fawx-0.0.5.dist-info/WHEEL
fawx-0.0.5.dist-info/top_level.txt
fawx-0.0.5.dist-info/RECORD
